{
  "type": "Child Care - Pre School",
  "centerName": "ECO 4 KIDS LLC ",
  "permitHolder": "ECO 4 KIDS LLC",
  "address": "4712 AVENUE N",
  "borough": "BROOKLYN",
  "zipCode": "11234",
  "phone": "718-252-8400",
  "permitStatus": " Permitted ",
  "permitNumber": "99877",
  "permitExpirationDate": " 11/13/2017",
  "ageRange": "2 - 5",
  "maximumCapacity": "19",
  "siteType": "Private",
  "certifiedToAdministerMedication": "No",
  "yearsOperating": "1",
  "hasInspections": "false",
  "latestInspection": {
    "date": "",
    "result": "",
    "infractions": "",
    "numInfractions": ""
  },
  "numInspections": "0",
  "pastInspections": "",
  "latitude": 40.618769028588,
  "longitude": -73.929558240697
}