{
  "type": "Child Care - Pre School",
  "centerName": "EUREKA NURSERY DAY CARE ",
  "permitHolder": "EUREKA NURSERY DAY CARE",
  "address": "2502 CLARENDON ROAD ",
  "borough": "BROOKLYN",
  "zipCode": "11226",
  "phone": "718-284-2155",
  "permitStatus": " Permitted ",
  "permitNumber": "7347",
  "permitExpirationDate": " 05/10/2016",
  "ageRange": "2 - 5",
  "maximumCapacity": "26",
  "siteType": "Private",
  "certifiedToAdministerMedication": "No",
  "yearsOperating": "12 or more",
  "hasInspections": "true",
  "latestInspection": {
    "date": "Inspection Date 12/23/2015",
    "result": "Inspection Result Initial Annual Inspection - Reinspection Required Fines pending",
    "numInfractions": "2",
    "infractions": [
      {
        "Violation Summary ": "Fire extinguishers observed not to be inspected or maintained at time of inspection",
        "Category ": " Violations requiring immediate correction Public Health Hazards ",
        "Code Sub-Section": "4759 b",
        " Status": "OPEN "
      },
      {
        "Violation Summary ": "At time of inspection floors/walls ceilings were observed not maintained in disrepair or covered in a toxic finish",
        "Category ": " Minor violations General Violations ",
        "Code Sub-Section": "4741 j",
        " Status": "OPEN "
      }
    ]
  },
  "numInspections": "11",
  "pastInspections": [
    {
      "date": "06/16/2015",
      "type": " Compliance Inspection of Open Violations",
      "result": "Reinspection Required Violations corrected at time of inspection ",
      "numViolations": "2",
      "violations": [
        {
          "Violation Summary ": "Exits and other egress not provided with required signage at time of inspection",
          "Category ": " Violations requiring correction within two weeks Critical Violations",
          "Code Sub-Section": "4759 a",
          " Status ": "CORRECTED"
        },
        {
          "Violation Summary ": "At time of inspection it was determined/observed that food service worker not provided with appropriate food thermometer during food prep",
          "Category ": " Minor violations General Violations",
          "Code Sub-Section": "8109 i",
          " Status ": "CORRECTED"
        }
      ]
    },
    {
      "date": "06/05/2015",
      "type": " Initial Annual Inspection",
      "result": "Reinspection Required ",
      "numViolations": "2",
      "violations": [
        {
          "Violation Summary ": "Exits and other egress not provided with required signage at time of inspection",
          "Category ": " Violations requiring correction within two weeks Critical Violations",
          "Code Sub-Section": "4759 a",
          " Status ": "CORRECTED"
        },
        {
          "Violation Summary ": "At time of inspection it was determined/observed that food service worker not provided with appropriate food thermometer during food prep",
          "Category ": " Minor violations General Violations",
          "Code Sub-Section": "8109 i",
          " Status ": "CORRECTED"
        }
      ]
    },
    {
      "date": "11/26/2014",
      "type": " Compliance Inspection of Open Violations",
      "result": "Reinspection Required Violations corrected at time of inspection ",
      "violations": "",
      "numViolations": "0"
    },
    {
      "date": "11/13/2014",
      "type": " Compliance Inspection of Open Violations",
      "result": "Reinspection Required Fines pending ",
      "numViolations": "3",
      "violations": [
        {
          "Violation Summary ": "Fire extinguishers observed not to be inspected or maintained at time of inspection",
          "Category ": " Violations requiring immediate correction Public Health Hazards",
          "Code Sub-Section": "4759 b",
          " Status ": "CORRECTED"
        },
        {
          "Violation Summary ": "At time of inspection floors/walls ceilings were observed not maintained in disrepair or covered in a toxic finish",
          "Category ": " Minor violations General Violations",
          "Code Sub-Section": "4741 j",
          " Status ": "CORRECTED"
        },
        {
          "Violation Summary ": "At time of inspection child care service failed to provide sufficient lighting and or failed to maintain adequate foot candles in areas used by children",
          "Category ": " Minor violations General Violations",
          "Code Sub-Section": "4745 b",
          " Status ": "CORRECTED"
        }
      ]
    },
    {
      "date": "10/31/2014",
      "type": " Initial Annual Inspection",
      "result": "Reinspection Required ",
      "numViolations": "3",
      "violations": [
        {
          "Violation Summary ": "Fire extinguishers observed not to be inspected or maintained at time of inspection",
          "Category ": " Violations requiring immediate correction Public Health Hazards",
          "Code Sub-Section": "4759 b",
          " Status ": "CORRECTED"
        },
        {
          "Violation Summary ": "At time of inspection floors/walls ceilings were observed not maintained in disrepair or covered in a toxic finish",
          "Category ": " Minor violations General Violations",
          "Code Sub-Section": "4741 j",
          " Status ": "CORRECTED"
        },
        {
          "Violation Summary ": "At time of inspection child care service failed to provide sufficient lighting and or failed to maintain adequate foot candles in areas used by children",
          "Category ": " Minor violations General Violations",
          "Code Sub-Section": "4745 b",
          " Status ": "CORRECTED"
        }
      ]
    },
    {
      "date": "05/29/2014",
      "type": " Initial Annual Inspection",
      "result": "Reinspection Not Required ",
      "violations": "",
      "numViolations": "0"
    },
    {
      "date": "04/03/2014",
      "type": " Compliance Inspection of Open Violations",
      "result": "Reinspection Required Violations corrected at time of inspection ",
      "violations": "",
      "numViolations": "0"
    },
    {
      "date": "03/21/2014",
      "type": " Initial Annual Inspection",
      "result": "Reinspection Required ",
      "violations": "",
      "numViolations": "0"
    },
    {
      "date": "09/11/2013",
      "type": " Initial Annual Inspection",
      "result": "Passed inspection with no violations ",
      "violations": "",
      "numViolations": "0"
    },
    {
      "date": "04/12/2013",
      "type": " Initial Annual Inspection",
      "result": "Reinspection Not Required ",
      "violations": "",
      "numViolations": "0"
    }
  ],
  "latitude": 40.642940796118,
  "longitude": -73.953401306598
}