{
  "type": "Camp",
  "centerName": "FIAO BEACON MARLBOROHOUSING ",
  "permitHolder": "FIAO BEACON MARLBOROHOUSING",
  "address": "2298 WEST 8TH STREET",
  "borough": "BROOKLYN",
  "zipCode": "11223",
  "phone": "718-333-0575",
  "permitStatus": " Registered ",
  "permitNumber": "34062",
  "permitExpirationDate": " 06/08/2015",
  "ageRange": "",
  "maximumCapacity": "0",
  "siteType": "Summer Day Camp",
  "certifiedToAdministerMedication": "No",
  "yearsOperating": "",
  "hasInspections": "true",
  "latestInspection": {
    "date": "Inspection Date 08/13/2013",
    "result": "Inspection Result Initial Annual Inspection - Reinspection Required",
    "numInfractions": "0",
    "infractions": [

    ]
  },
  "numInspections": "1",
  "pastInspections": "",
  "latitude": 40.592073665558,
  "longitude": -73.978468366281
}