{
  "type": "Child Care - Pre School",
  "centerName": "GREAT BEGINNINGS INFANT TODDLER CENTER ",
  "permitHolder": "BJB OF NEW YORK INC",
  "address": "2221 RICHMOND AVENUE ",
  "borough": "STATEN ISLAND",
  "zipCode": "10314",
  "phone": "718-983-0014",
  "permitStatus": " Permitted ",
  "permitNumber": "10997",
  "permitExpirationDate": " 01/11/2016",
  "ageRange": "2 - 5",
  "maximumCapacity": "12",
  "siteType": "Private",
  "certifiedToAdministerMedication": "No",
  "yearsOperating": "4 ",
  "hasInspections": "true",
  "latestInspection": {
    "date": "Inspection Date 07/01/2015",
    "result": "Inspection Result Initial Annual Inspection - Reinspection Not Required",
    "numInfractions": "1",
    "infractions": [
      {
        "Violation Summary ": "Child care service failed to provide or maintain record of staff immunizations",
        "Category ": " Minor violations General Violations ",
        "Code Sub-Section": "4733 c",
        " Status": "CORRECTED"
      }
    ]
  },
  "numInspections": "10",
  "pastInspections": [
    {
      "date": "06/02/2015",
      "type": " Initial Annual Inspection",
      "result": "Passed inspection with no violations ",
      "violations": "",
      "numViolations": "0"
    },
    {
      "date": "11/20/2014",
      "type": " Initial Annual Inspection",
      "result": "Passed inspection with no violations ",
      "violations": "",
      "numViolations": "0"
    },
    {
      "date": "05/13/2014",
      "type": " Monitoring Inspection Non-Routine",
      "result": "Passed inspection with no violations ",
      "violations": "",
      "numViolations": "0"
    },
    {
      "date": "02/06/2014",
      "type": " Initial Annual Inspection",
      "result": "Passed inspection with no violations ",
      "violations": "",
      "numViolations": "0"
    },
    {
      "date": "09/25/2013",
      "type": " Initial Annual Inspection",
      "result": "Passed inspection with no violations ",
      "violations": "",
      "numViolations": "0"
    },
    {
      "date": "09/25/2013",
      "type": " Initial Annual Inspection",
      "result": "Passed inspection with no violations ",
      "violations": "",
      "numViolations": "0"
    },
    {
      "date": "02/26/2013",
      "type": " Initial Annual Inspection",
      "result": "Reinspection Required ",
      "violations": "",
      "numViolations": "0"
    },
    {
      "date": "02/26/2013",
      "type": " Initial Annual Inspection",
      "result": "Passed inspection with no violations ",
      "violations": "",
      "numViolations": "0"
    },
    {
      "date": "01/24/2013",
      "type": " Initial Annual Inspection",
      "result": "Passed inspection with no violations ",
      "violations": "",
      "numViolations": "0"
    }
  ],
  "latitude": 40.592640169393,
  "longitude": -74.163123411322
}