{
  "type": "Child Care - Pre School",
  "centerName": "LA PENINSULA COMMUNITY ORGANIZATION HEAD START PROGRAM 2 ",
  "permitHolder": "LA PENINSULA COMMUNITY ORGANIZATION INC",
  "address": "1054 INTERVALE AVENUE",
  "borough": "BRONX",
  "zipCode": "10459",
  "phone": "718-893-5074",
  "permitStatus": " Permitted ",
  "permitNumber": "4780",
  "permitExpirationDate": " 06/08/2017",
  "ageRange": "2 - 5",
  "maximumCapacity": "110",
  "siteType": "ACS Contracted Preschools",
  "certifiedToAdministerMedication": "No",
  "yearsOperating": "13 or more",
  "hasInspections": "true",
  "latestInspection": {
    "date": "Inspection Date 03/17/2015",
    "result": "Inspection Result Compliance Inspection of Open Violations - Previously cited violations corrected",
    "numInfractions": "0",
    "infractions": [

    ]
  },
  "numInspections": "8",
  "pastInspections": [
    {
      "date": "03/03/2015",
      "type": " Initial Annual Inspection",
      "result": "Reinspection Required ",
      "violations": "",
      "numViolations": "0"
    },
    {
      "date": "03/20/2014",
      "type": " Compliance Inspection of Open Violations",
      "result": "Previously cited violations corrected ",
      "violations": "",
      "numViolations": "0"
    },
    {
      "date": "02/28/2014",
      "type": " Initial Annual Inspection",
      "result": "Reinspection Not Required ",
      "violations": "",
      "numViolations": "0"
    },
    {
      "date": "02/19/2014",
      "type": " Initial Annual Inspection",
      "result": "Reinspection Required ",
      "violations": "",
      "numViolations": "0"
    },
    {
      "date": "03/15/2013",
      "type": " Compliance Inspection of Open Violations",
      "result": "Previously cited violations corrected ",
      "violations": "",
      "numViolations": "0"
    },
    {
      "date": "03/05/2013",
      "type": " Compliance Inspection of Open Violations",
      "result": "Reinspection Required ",
      "violations": "",
      "numViolations": "0"
    },
    {
      "date": "02/13/2013",
      "type": " Initial Annual Inspection",
      "result": "Reinspection Required ",
      "violations": "",
      "numViolations": "0"
    }
  ],
  "latitude": 40.824815891086,
  "longitude": -73.896838079211
}