{
  "type": "Child Care - Infants/Toddlers",
  "centerName": "LITTLE MUNCHKINS PLAYGROUP 56 INC ",
  "permitHolder": "LITTLE MUNCHKINS PLAYGROUP 56 INC",
  "address": "1460 56TH STREET",
  "borough": "BROOKLYN",
  "zipCode": "11219",
  "phone": "718-437-7261",
  "permitStatus": " Permitted ",
  "permitNumber": "55817",
  "permitExpirationDate": " 01/07/2018",
  "ageRange": "0 - 2",
  "maximumCapacity": "43",
  "siteType": "Private",
  "certifiedToAdministerMedication": "No",
  "yearsOperating": "2",
  "hasInspections": "true",
  "latestInspection": {
    "date": "Inspection Date 12/21/2015",
    "result": "Inspection Result Initial Annual Inspection - Reinspection Not Required",
    "numInfractions": "1",
    "infractions": [
      {
        "Violation Summary ": "Child care service failed to provide or maintain record of staff immunizations",
        "Category ": " Minor violations General Violations ",
        "Code Sub-Section": "4733 c",
        " Status": "CORRECTED"
      }
    ]
  },
  "numInspections": "7",
  "pastInspections": [
    {
      "date": "10/19/2015",
      "type": " Initial Annual Inspection",
      "result": "Reinspection Not Required ",
      "violations": "",
      "numViolations": "0"
    },
    {
      "date": "09/04/2015",
      "type": " Initial Annual Inspection",
      "result": "Passed inspection with no violations ",
      "violations": "",
      "numViolations": "0"
    },
    {
      "date": "01/13/2015",
      "type": " Compliance Inspection of Open Violations",
      "result": "Previously cited violations corrected ",
      "numViolations": "3",
      "violations": [
        {
          "Violation Summary ": "Required food protection procedures were not implemented at time of inspection Holder of food protection certificate was not on site during hours of food preparation activity",
          "Category ": " Violations requiring immediate correction Public Health Hazards",
          "Code Sub-Section": "4761 a",
          " Status ": "CORRECTED"
        },
        {
          "Violation Summary ": "Child care service observed providing care to infant/toddlers in a location above or below the ground floor without required approvals",
          "Category ": " Violations requiring correction within two weeks Critical Violations",
          "Code Sub-Section": "4741 c",
          " Status ": "CORRECTED"
        },
        {
          "Violation Summary ": "At time of inspection floors/walls ceilings were observed not maintained in disrepair or covered in a toxic finish",
          "Category ": " Minor violations General Violations",
          "Code Sub-Section": "4741 j",
          " Status ": "CORRECTED"
        }
      ]
    },
    {
      "date": "10/01/2014",
      "type": " Initial Annual Inspection",
      "result": "Passed inspection with no violations ",
      "violations": "",
      "numViolations": "0"
    },
    {
      "date": "09/05/2014",
      "type": " Initial Annual Inspection",
      "result": "Reinspection Not Required ",
      "violations": "",
      "numViolations": "0"
    },
    {
      "date": "05/01/2014",
      "type": " Initial Annual Inspection",
      "result": "Reinspection Required ",
      "numViolations": "2",
      "violations": [
        {
          "Violation Summary ": "Child care service failed to arrange/conduct criminal/SCR background clearance checks for required individuals failed to re-clear required individuals with the SCR every two years",
          "Category ": " Violations requiring immediate correction Public Health Hazards",
          "Code Sub-Section": "4719 c",
          " Status ": "CORRECTED"
        },
        {
          "Violation Summary ": "At time of inspection it was determined that child care service allows staff to perform their duties that are not healthy or are incapable of carrying out their duties Staff medical clearances are not maintained by child care service",
          "Category ": " Violations requiring correction within two weeks Critical Violations",
          "Code Sub-Section": "4733 b",
          " Status ": "CORRECTED"
        }
      ]
    }
  ],
  "latitude": 40.628992824929,
  "longitude": -73.992726336278
}