{
  "type": "Child Care - Infants/Toddlers",
  "centerName": "LITTLE SCHOLARS LEARNING CENTER ",
  "permitHolder": "M AND N CHILD CARE, INC.",
  "address": "50 QUENTIN ROAD",
  "borough": "BROOKLYN",
  "zipCode": "11223",
  "phone": "718-373-7046",
  "permitStatus": "\r\n                    Permitted\r\n                    ",
  "permitNumber": "49897",
  "permitExpirationDate": " 08/09/2017",
  "ageRange": "0 - 2",
  "maximumCapacity": "15",
  "siteType": "Private",
  "certifiedToAdministerMedication": "No",
  "yearsOperating": "2         ",
  "hasInspections": true,
  "latestInspection": {
    "date": "<tr class=\"odd gradeX\">\r\n                        <td>Inspection Date:      10/07/2015</td>\r\n                        <td>                          \r\n                                                \r\n                        </td>\r\n                        \r\n                      </tr>",
    "result": "<tr class=\"even gradeC\">\r\n                        <td>Inspection Result:      Initial Annual Inspection - Reinspection Not Required\t</td>\r\n                        <td>    \r\n                                                                     \r\n                        <!-- VISIT&nbsp;- -->\r\n\t\t\t\t\t\t\r\n\t\t\t\t\t\t\t\t\t\t\t\t\t\t\t\t\t\t\r\n\t\t\t\t\t\t</td>\r\n                      </tr>",
    "numInfractions": 1,
    "infractions": [
      {
        "Violation Summary ": "Child care service staff identified/acting as group teachers do not meet the required qualifications of the position",
        "Category ": "                                                         Minor violations General Violations                            ",
        "Code Sub-Section": "4713 d",
        " Status": "OPEN "
      }
    ]
  }
}