{
  "type": "Child Care - Infants/Toddlers",
  "centerName": "M. KALIX AND NATALIE LINDOR NURSERY INC. I/T ",
  "permitHolder": "MAGALIE EARLY INTERVENTION DEVELOPMENTAL CENTER INC I/T",
  "address": "\r\n\t\t\t\t\t\r\n\t\t\t\t\t951 EAST 84TH STREET      \t\t\t  \r\n\t\t\t\t\t\t\t\t\r\n\t\t\t\t\t",
  "borough": "BROOKLYN",
  "zipCode": "11236",
  "phone": "718-209-1347",
  "permitStatus": "\r\n                    Permitted\r\n                    ",
  "permitNumber": "8101",
  "permitExpirationDate": " 12/21/2015",
  "ageRange": "0 - 2",
  "maximumCapacity": "44",
  "siteType": "Private",
  "certifiedToAdministerMedication": "No",
  "yearsOperating": "6         ",
  "hasInspections": true,
  "latestInspection": {
    "date": "<tr class=\"odd gradeX\">\r\n                        <td>Inspection Date:      11/12/2015</td>\r\n                        <td>                          \r\n                                                \r\n                        </td>\r\n                        \r\n                      </tr>",
    "result": "<tr class=\"even gradeC\">\r\n                        <td>Inspection Result:      Initial Annual Inspection - Reinspection Required\t</td>\r\n                        <td>    \r\n                                                                     \r\n                        <!-- VISIT&nbsp;- -->\r\n\t\t\t\t\t\t\r\n\t\t\t\t\t\t\t\t\t\t\t\t\t\t\t\t\t\t\r\n\t\t\t\t\t\t</td>\r\n                      </tr>",
    "numInfractions": 4,
    "infractions": [
      {
        "Violation Summary ": "Child care service failed to arrange/conduct criminal/SCR background clearance checks for required individuals failed to re-clear required individuals with the SCR every two years",
        "Category ": "                                                         Violations requiring immediate correction Public Health Hazards                            ",
        "Code Sub-Section": "4719 c",
        " Status": "OPEN "
      },
      {
        "Violation Summary ": "At time of inspection it was determined that child care service allows staff to perform their duties that are not healthy or are incapable of carrying out their duties Staff medical clearances are not maintained by child care service",
        "Category ": "                                                         Violations requiring correction within two weeks Critical Violations                            ",
        "Code Sub-Section": "4733 b",
        " Status": "OPEN "
      },
      {
        "Violation Summary ": "Child care service failed to conduct business and employment reference checks of staff/volunteers",
        "Category ": "                                                         Minor violations General Violations                            ",
        "Code Sub-Section": "4719 i",
        " Status": "OPEN "
      },
      {
        "Violation Summary ": "Child care service failed to provide or maintain record of staff immunizations",
        "Category ": "                                                         Minor violations General Violations                            ",
        "Code Sub-Section": "4733 c",
        " Status": "OPEN "
      }
    ]
  }
}