{
  "type": "Child Care - Pre School",
  "centerName": "MACEDONIA CHILD DEVELOPMENT CENTER ",
  "permitHolder": "GREATER FLUSHING COMMUNITY COUNCIL,INC.",
  "address": "37-22 UNION STREET",
  "borough": "QUEENS",
  "zipCode": "11354",
  "phone": "718-939-6060",
  "permitStatus": "\r\n                    Permitted\r\n                    ",
  "permitNumber": "3015",
  "permitExpirationDate": " 05/07/2016",
  "ageRange": "2 - 5",
  "maximumCapacity": "35",
  "siteType": "ACS Contracted Preschools",
  "certifiedToAdministerMedication": "No",
  "yearsOperating": "11 or more",
  "hasInspections": true,
  "latestInspection": {
    "date": "<tr class=\"odd gradeX\">\r\n                        <td>Inspection Date:      06/10/2015</td>\r\n                        <td>                          \r\n                                                \r\n                        </td>\r\n                        \r\n                      </tr>",
    "result": "<tr class=\"even gradeC\">\r\n                        <td>Inspection Result:      Initial Annual Inspection - Passed inspection with no violations\t</td>\r\n                        <td>    \r\n                                                                     \r\n                        <!-- INSPECTION&nbsp;- -->\r\n\t\t\t\t\t\t\r\n\t\t\t\t\t\t\t\t\t\t\t\t\t\t\t\t\t\t\r\n\t\t\t\t\t\t</td>\r\n                      </tr>",
    "numInfractions": 0,
    "infractions": [

    ]
  }
}