{
  "type": "Camp",
  "centerName": "MONTESSORI FAMILY SCHOOL SUMMER DAY CAMP ",
  "permitHolder": "MONTESSORI FAMILY SCHOOL OF MANHATTAN",
  "address": "\r\n\t\t\t\t\t\r\n\t\t\t\t\t323 EAST 47TH STREET      \t\t\t  \r\n\t\t\t\t\t\t\t\t\r\n\t\t\t\t\t",
  "borough": "MANHATTAN",
  "zipCode": "10017",
  "phone": "212-688-5950",
  "permitStatus": "\r\n                    In-Renewal\r\n                    ",
  "permitNumber": "34165",
  "permitExpirationDate": " 09/15/2015",
  "ageRange": "4 - 16",
  "maximumCapacity": "95",
  "siteType": "Summer Day Camp",
  "certifiedToAdministerMedication": "No",
  "yearsOperating": "2 or more",
  "hasInspections": true,
  "latestInspection": {
    "date": "<tr class=\"odd gradeX\">\r\n                        <td>Inspection Date:      06/22/2015</td>\r\n                        <td>                          \r\n                                                \r\n                        </td>\r\n                        \r\n                      </tr>",
    "result": "<tr class=\"even gradeC\">\r\n                        <td>Inspection Result:      Initial Annual Inspection - Reinspection Required\t</td>\r\n                        <td>    \r\n                                                                     \r\n                        <!-- INSPECTION&nbsp;- -->\r\n\t\t\t\t\t\t\r\n\t\t\t\t\t\t\t\t\t\t\t\t\t\t\t\t\t\t\r\n\t\t\t\t\t\t</td>\r\n                      </tr>",
    "numInfractions": 5,
    "infractions": [
      {
        "Violation Summary ": "Fire extinguishers not provided have not been inspected and tagged prior to camp season",
        "Category ": "                                                         Violations requiring immediate correction Public Health Hazards                            ",
        "Code Sub-Section": "4815a8",
        " Status": "OPEN "
      },
      {
        "Violation Summary ": "Sufficient handwash sinks with hot and cold running water liquid soap drying devices not provided in comercial buildings",
        "Category ": "                                                         Violations requiring correction within two weeks Critical Violations                            ",
        "Code Sub-Section": "13109d2",
        " Status": "OPEN "
      },
      {
        "Violation Summary ": "Exits from areas with 15 or more persons or not readily visible are not identified by lighted signs and directional signs as required",
        "Category ": "                                                         Violations requiring correction within two weeks Critical Violations                            ",
        "Code Sub-Section": "4815a15",
        " Status": "OPEN "
      },
      {
        "Violation Summary ": "Emergency lighting in halls stairs not provided where required",
        "Category ": "                                                         Violations requiring correction within two weeks Critical Violations                            ",
        "Code Sub-Section": "4815a16",
        " Status": "OPEN "
      },
      {
        "Violation Summary ": "Camp Director fails to conduct inspection of fire protection facilities and equipment",
        "Category ": "                                                         Minor violations General Violations                            ",
        "Code Sub-Section": "4815a1",
        " Status": "OPEN "
      }
    ]
  }
}