{
  "type": "Camp",
  "centerName": "NEW LIFE CHILD DEVE DAY CARE CTR 2 ",
  "permitHolder": "NEW LIFE CHILD DEVE DAY CARE CTR 2",
  "address": "406-408 GROVE STREET",
  "borough": "BROOKLYN",
  "zipCode": "11237",
  "phone": "718-417-4206",
  "permitStatus": " Registered ",
  "permitNumber": "5349",
  "permitExpirationDate": " 01/15/2016",
  "ageRange": "",
  "maximumCapacity": "89",
  "siteType": "Summer Day Camp",
  "certifiedToAdministerMedication": "No",
  "yearsOperating": "",
  "hasInspections": "true",
  "latestInspection": {
    "date": "Inspection Date 08/07/2013",
    "result": "Inspection Result Initial Annual Inspection - Reinspection Required",
    "numInfractions": "0",
    "infractions": [

    ]
  },
  "numInspections": "2",
  "pastInspections": [
    {
      "date": "05/10/2013",
      "type": " Monitoring Inspection Non-Routine",
      "result": "Passed inspection with no violations ",
      "violations": "",
      "numViolations": "0"
    }
  ]
}