{
  "type": "Child Care - Pre School",
  "centerName": "NY CITY EXPLORERS PRE-KADEMY INC ",
  "permitHolder": "NY CITY EXPLORERS PRE-KADEMY INC",
  "address": "110 SCHERMERHORN ST ",
  "borough": "BROOKLYN",
  "zipCode": "11201",
  "phone": "855-687-6923",
  "permitStatus": " Permitted ",
  "permitNumber": "72985",
  "permitExpirationDate": " 09/05/2016",
  "ageRange": "2 - 5",
  "maximumCapacity": "46",
  "siteType": "Private",
  "certifiedToAdministerMedication": "No",
  "yearsOperating": "1",
  "hasInspections": "true",
  "latestInspection": {
    "date": "Inspection Date 05/05/2015",
    "result": "Inspection Result Initial Annual Inspection - Reinspection Not Required",
    "numInfractions": "3",
    "infractions": [
      {
        "Violation Summary ": "At time of inspection it was observed that child care service failed to provide appropriate guards on designated structures/equipment to protect children from potential injury",
        "Category ": " Violations requiring correction within two weeks Critical Violations ",
        "Code Sub-Section": "4741 h",
        " Status": "CORRECTED"
      },
      {
        "Violation Summary ": "At time of inspection floors/walls ceilings were observed not maintained in disrepair or covered in a toxic finish",
        "Category ": " Minor violations General Violations ",
        "Code Sub-Section": "4741 j",
        " Status": "OPEN "
      },
      {
        "Violation Summary ": "At time of inspection child care service failed to provide sufficient lighting and or failed to maintain adequate foot candles in areas used by children",
        "Category ": " Minor violations General Violations ",
        "Code Sub-Section": "4745 b",
        " Status": "OPEN "
      }
    ]
  },
  "numInspections": "1",
  "pastInspections": ""
}