{
  "type": "Camp",
  "centerName": "A CHILDS PLACE ",
  "permitHolder": "A CHILDS PLACE",
  "address": "32-20 108 STREET",
  "borough": "QUEENS",
  "zipCode": "11369",
  "phone": "",
  "permitStatus": " Registered ",
  "permitNumber": "N/A",
  "permitExpirationDate": " N/A",
  "ageRange": "",
  "maximumCapacity": "0",
  "siteType": "Summer Day Camp",
  "certifiedToAdministerMedication": "No",
  "yearsOperating": "",
  "hasInspections": "false",
  "latestInspection": {
    "date": "",
    "result": "",
    "infractions": "",
    "numInfractions": ""
  },
  "numInspections": "0",
  "pastInspections": ""
}