{
  "type": "Child Care - Pre School",
  "centerName": "PROVIDENCE REST CHILD DAY CARE CENTER INC ",
  "permitHolder": "PROVIDENCE REST CHILD DAY CARE CENTER INC",
  "address": "3310 CAMPBELL DRIVE",
  "borough": "BRONX",
  "zipCode": "10465",
  "phone": "718-823-3588",
  "permitStatus": " Permitted ",
  "permitNumber": "5871",
  "permitExpirationDate": " 11/09/2017",
  "ageRange": "2 - 5",
  "maximumCapacity": "25",
  "siteType": "Private",
  "certifiedToAdministerMedication": "No",
  "yearsOperating": "11 or more",
  "hasInspections": "true",
  "latestInspection": {
    "date": "Inspection Date 09/30/2015",
    "result": "Inspection Result Initial Annual Inspection - Reinspection Not Required",
    "numInfractions": "2",
    "infractions": [
      {
        "Violation Summary ": "Child care service failed to provide or maintain record of staff immunizations",
        "Category ": " Minor violations General Violations ",
        "Code Sub-Section": "4733 c",
        " Status": "CORRECTED"
      },
      {
        "Violation Summary ": "At time of inspection it was determined that child care service failed to ensure staff received required training within time frames and/or failed to maintain training records",
        "Category ": " Minor violations General Violations ",
        "Code Sub-Section": "4737 b1",
        " Status": "CORRECTED"
      }
    ]
  },
  "numInspections": "6",
  "pastInspections": [
    {
      "date": "05/01/2015",
      "type": " Initial Annual Inspection",
      "result": "Passed inspection with no violations ",
      "violations": "",
      "numViolations": "0"
    },
    {
      "date": "07/11/2014",
      "type": " Initial Annual Inspection",
      "result": "Passed inspection with no violations ",
      "violations": "",
      "numViolations": "0"
    },
    {
      "date": "10/31/2013",
      "type": " Initial Annual Inspection",
      "result": "Reinspection Required ",
      "violations": "",
      "numViolations": "0"
    },
    {
      "date": "03/06/2013",
      "type": " Initial Annual Inspection",
      "result": "Passed inspection with no violations ",
      "violations": "",
      "numViolations": "0"
    },
    {
      "date": "02/05/2013",
      "type": " Initial Annual Inspection",
      "result": "Reinspection Required ",
      "violations": "",
      "numViolations": "0"
    }
  ],
  "latitude": 40.838246040781,
  "longitude": -73.81746847368
}