{
  "type": "Camp",
  "centerName": "PS 165 OF THE CENTRAL QUEENS Y ",
  "permitHolder": "PS 165 OF THE CENTRAL QUEENS Y",
  "address": "70-35 150TH STREET",
  "borough": "QUEENS",
  "zipCode": "11367",
  "phone": "718-268-5011",
  "permitStatus": " Registered ",
  "permitNumber": "N/A",
  "permitExpirationDate": " 02/12/2014",
  "ageRange": "",
  "maximumCapacity": "0",
  "siteType": "Summer Day Camp",
  "certifiedToAdministerMedication": "No",
  "yearsOperating": "",
  "hasInspections": "true",
  "latestInspection": {
    "date": "Inspection Date 08/01/2013",
    "result": "Inspection Result Initial Annual Inspection - Passed inspection with no violations",
    "numInfractions": "0",
    "infractions": [

    ]
  },
  "numInspections": "1",
  "pastInspections": [

  ],
  "latitude": 40.730107178118,
  "longitude": -73.818638990168
}