{
  "type": "Camp",
  "centerName": "SCO FAMILY SERVICES-FAMILY DYNAMICS ",
  "permitHolder": "SCO FAMILY OF SERVICES",
  "address": "820 HANCOCK ST",
  "borough": "BROOKLYN",
  "zipCode": "11233",
  "phone": "718-443-8527",
  "permitStatus": " In-Renewal ",
  "permitNumber": "34139",
  "permitExpirationDate": " 09/15/2015",
  "ageRange": "4 - 16",
  "maximumCapacity": "170",
  "siteType": "Summer Day Camp",
  "certifiedToAdministerMedication": "No",
  "yearsOperating": "2 or more",
  "hasInspections": "true",
  "latestInspection": {
    "date": "Inspection Date 07/27/2015",
    "result": "Inspection Result Initial Annual Inspection - Passed inspection with no violations",
    "numInfractions": "0",
    "infractions": [

    ]
  },
  "numInspections": "3",
  "pastInspections": [
    {
      "date": "08/04/2014",
      "type": " Compliance Inspection of Open Violations",
      "result": "Reinspection Not Required ",
      "numViolations": "2",
      "violations": [
        {
          "Violation Summary ": "Health Director not qualified MD Nurse EMT Health Director not on site at overnight camp not available to summer day and traveling camps Assistant was not designated where required",
          "Category ": " Violations requiring immediate correction Public Health Hazards",
          "Code Sub-Section": "4817p",
          " Status ": "CORRECTED"
        },
        {
          "Violation Summary ": "All camp staff have not had recent medical exam including TB testing as required by the Dept",
          "Category ": " Minor violations General Violations",
          "Code Sub-Section": "4817g",
          " Status ": "CORRECTED"
        }
      ]
    },
    {
      "date": "07/23/2014",
      "type": " Initial Annual Inspection",
      "result": "Reinspection Required Fines pending ",
      "numViolations": "2",
      "violations": [
        {
          "Violation Summary ": "Health Director not qualified MD Nurse EMT Health Director not on site at overnight camp not available to summer day and traveling camps Assistant was not designated where required",
          "Category ": " Violations requiring immediate correction Public Health Hazards",
          "Code Sub-Section": "4817p",
          " Status ": "CORRECTED"
        },
        {
          "Violation Summary ": "All camp staff have not had recent medical exam including TB testing as required by the Dept",
          "Category ": " Minor violations General Violations",
          "Code Sub-Section": "4817g",
          " Status ": "CORRECTED"
        }
      ]
    }
  ],
  "latitude": 40.685687690312,
  "longitude": -73.922463405704
}