{
  "type": "Child Care - Pre School",
  "centerName": "BUSHWICK UNITED HEAD START ",
  "permitHolder": "BUSHWICK UNITED HOUSING DEVELOPMENT FUND CORPORATION",
  "address": "200 CENTRAL AVENUE",
  "borough": "BROOKLYN",
  "zipCode": "11221",
  "phone": "718-453-5500",
  "permitStatus": "\r\n                    Permitted\r\n                    ",
  "permitNumber": "23599",
  "permitExpirationDate": " 09/29/2016",
  "ageRange": "2 - 5",
  "maximumCapacity": "130",
  "siteType": "ACS Contracted Preschools",
  "certifiedToAdministerMedication": "No",
  "yearsOperating": "3         ",
  "hasInspections": true,
  "latestInspection": {
    "date": "<tr class=\"odd gradeX\">\r\n                        <td>Inspection Date:      10/15/2015</td>\r\n                        <td>                          \r\n                                                \r\n                        </td>\r\n                        \r\n                      </tr>",
    "result": "<tr class=\"even gradeC\">\r\n                        <td>Inspection Result:      Compliance Inspection of Open Violations - Reinspection Required; Violations corrected at time of inspection\t</td>\r\n                        <td>    \r\n                                                                     \r\n                        <!-- INSPECTION&nbsp;- -->\r\n\t\t\t\t\t\t\r\n\t\t\t\t\t\t\t\t\t\t\t\t\t\t\t\t\t\t\r\n\t\t\t\t\t\t</td>\r\n                      </tr>",
    "numInfractions": 1,
    "infractions": [
      {
        "Violation Summary ": "Exits and other egress not provided with required signage at time of inspection",
        "Category ": "                                                         Violations requiring correction within two weeks Critical Violations                            ",
        "Code Sub-Section": "4759 a",
        " Status": "CORRECTED"
      }
    ]
  }
}