{
  "type": "Camp",
  "centerName": "CAMP HENRY DAY CAMP ",
  "permitHolder": "HENRY STREET SETTLEMENT",
  "address": "301 HENRY STREET ",
  "borough": "MANHATTAN",
  "zipCode": "10002",
  "phone": "212-254-3100",
  "permitStatus": " In-Renewal ",
  "permitNumber": "34171",
  "permitExpirationDate": " 09/15/2014",
  "ageRange": "4 - 16",
  "maximumCapacity": "114",
  "siteType": "Summer Day Camp",
  "certifiedToAdministerMedication": "No",
  "yearsOperating": "3 or more",
  "hasInspections": "true",
  "latestInspection": {
    "date": "Inspection Date 08/06/2014",
    "result": "Inspection Result Initial Annual Inspection - Reinspection Required Violations corrected at time of inspection",
    "numInfractions": "2",
    "infractions": [
      {
        "Violation Summary ": "Facilty egress observed obstructed not protected from hazardous areas",
        "Category ": " Violations requiring immediate correction Public Health Hazards ",
        "Code Sub-Section": "4815a6",
        " Status": "CORRECTED"
      },
      {
        "Violation Summary ": "All windows except fire escape and emergency access windows not provided with guards in camps with children less than 10 years of age",
        "Category ": " Violations requiring immediate correction Public Health Hazards ",
        "Code Sub-Section": "4815d5",
        " Status": "CORRECTED"
      }
    ]
  },
  "numInspections": "2",
  "pastInspections": [
    {
      "date": "07/16/2013",
      "type": " Initial Annual Inspection",
      "result": "Reinspection Required Violations corrected at time of inspection ",
      "numViolations": "5",
      "violations": [
        {
          "Violation Summary ": "The owner or agent tenant or manager fails to maintain building in safe manner Structural integrety not maintained Building not free of pests Adequate heat ventilation and lighting not provided Not free of nuisances/hazards",
          "Category ": " Violations requiring immediate correction Public Health Hazards",
          "Code Sub-Section": "13105a",
          " Status ": "CORRECTED"
        },
        {
          "Violation Summary ": "Facilty egress observed obstructed not protected from hazardous areas",
          "Category ": " Violations requiring immediate correction Public Health Hazards",
          "Code Sub-Section": "4815a6",
          " Status ": "CORRECTED"
        },
        {
          "Violation Summary ": "All windows except fire escape and emergency access windows not provided with guards in camps with children less than 10 years of age",
          "Category ": " Violations requiring immediate correction Public Health Hazards",
          "Code Sub-Section": "4815d5",
          " Status ": "CORRECTED"
        },
        {
          "Violation Summary ": "Emergency lighting in halls stairs not provided where required",
          "Category ": " Violations requiring correction within two weeks Critical Violations",
          "Code Sub-Section": "4815a16",
          " Status ": "CORRECTED"
        },
        {
          "Violation Summary ": "Non overnight camps not provided with 1 toilet 30 females 1 toilet 1 urinal 60 males 1 lavatory 40 campers",
          "Category ": " Violations requiring correction within two weeks Critical Violations",
          "Code Sub-Section": "4815g2",
          " Status ": "CORRECTED"
        }
      ]
    }
  ],
  "latitude": 40.714046900234,
  "longitude": -73.982797158388
}