{
  "type": "School Based Child Care",
  "centerName": "CORLEARS SCHOOL ",
  "permitHolder": "CORLEARS SCHOOL",
  "address": "\r\n\t\t\t\t\t\r\n\t\t\t\t\t324 WEST 15 STREET      \t\t\t  \r\n\t\t\t\t\t\t\t\t\r\n\t\t\t\t\t",
  "borough": "MANHATTAN",
  "zipCode": "10011",
  "phone": "212-741-2800",
  "permitStatus": "\r\n                    Active\r\n                    ",
  "permitNumber": "3027",
  "permitExpirationDate": " 09/27/2010",
  "ageRange": "2 - 5",
  "maximumCapacity": "85",
  "siteType": "Private",
  "certifiedToAdministerMedication": "No",
  "yearsOperating": "",
  "hasInspections": true,
  "latestInspection": {
    "date": "<tr class=\"odd gradeX\">\r\n                        <td>Inspection Date:      11/12/2015</td>\r\n                        <td>                          \r\n                                                \r\n                        </td>\r\n                        \r\n                      </tr>",
    "result": "<tr class=\"even gradeC\">\r\n                        <td>Inspection Result:      Initial Annual Inspection - Reinspection Not Required\t</td>\r\n                        <td>    \r\n                                                                     \r\n                        <!-- INSPECTION&nbsp;- -->\r\n\t\t\t\t\t\t\r\n\t\t\t\t\t\t\t\t\t\t\t\t\t\t\t\t\t\t\r\n\t\t\t\t\t\t</td>\r\n                      </tr>",
    "numInfractions": 7,
    "infractions": [
      {
        "Violation Summary ": "The owner or agent tenant or manager fails to maintain building in safe manner Structural integrety not maintained Building not free of pests Adequate heat ventilation and lighting not provided Not free of nuisances/hazards",
        "Category ": "                                                         Violations requiring immediate correction Public Health Hazards                            ",
        "Code Sub-Section": "13105a",
        " Status": "CORRECTED"
      },
      {
        "Violation Summary ": "Hand wash sink not provided in food prep area Hand wash sink observed not maintained at time of inspection",
        "Category ": "                                                         Violations requiring correction within two weeks Critical Violations                            ",
        "Code Sub-Section": "8129 c",
        " Status": "CORRECTED"
      },
      {
        "Violation Summary ": "Food prep service observed with insufficient refrigerators and/or hot holding equipment at time of inspection",
        "Category ": "                                                         Violations requiring correction within two weeks Critical Violations                            ",
        "Code Sub-Section": "8135",
        " Status": "CORRECTED"
      },
      {
        "Violation Summary ": "Adequate lighting not provided in commercial building at time of inspection",
        "Category ": "                                                         Minor violations General Violations                            ",
        "Code Sub-Section": "13109a",
        " Status": "OPEN "
      },
      {
        "Violation Summary ": "Floors in comercial building properly not constructed not maintained in good repair unclean",
        "Category ": "                                                         Minor violations General Violations                            ",
        "Code Sub-Section": "13109e",
        " Status": "CORRECTED"
      },
      {
        "Violation Summary ": "At time of inspection it was determined/observed that food service worker not provided with appropriate food thermometer during food prep",
        "Category ": "                                                         Minor violations General Violations                            ",
        "Code Sub-Section": "8109 i",
        " Status": "CORRECTED"
      },
      {
        "Violation Summary ": "Appropriate methods to maintain food prep area free of pests was not provided or maintained at time of inspection",
        "Category ": "                                                         Minor violations General Violations                            ",
        "Code Sub-Section": "8123 c",
        " Status": "CORRECTED"
      }
    ]
  }
}